MANIFEST.in
README.md
setup.py
OctoPrint_Authentise.egg-info/PKG-INFO
OctoPrint_Authentise.egg-info/SOURCES.txt
OctoPrint_Authentise.egg-info/dependency_links.txt
OctoPrint_Authentise.egg-info/entry_points.txt
OctoPrint_Authentise.egg-info/not-zip-safe
OctoPrint_Authentise.egg-info/requires.txt
OctoPrint_Authentise.egg-info/top_level.txt
octoprint_authentise/__init__.py
octoprint_authentise/asset.py
octoprint_authentise/blueprint.py
octoprint_authentise/comm.py
octoprint_authentise/helpers.py
octoprint_authentise/settings.py
octoprint_authentise/startup.py
octoprint_authentise/template.py
octoprint_authentise/update.py
octoprint_authentise/version.py
octoprint_authentise/static/img/authentise_logo.png
octoprint_authentise/static/js/connect.js
octoprint_authentise/static/js/models.js
octoprint_authentise/static/less/authentise.less
octoprint_authentise/templates/authentise_generic.jinja2
octoprint_authentise/templates/authentise_settings.jinja2
octoprint_authentise/templates/authentise_tab.jinja2