Metadata-Version: 1.0
Name: OctoPrint-Authentise
Version: 0.8
Summary: Authenitse Octoprint Integration
Home-page: https://github.com/authentise/OctoPrint-Authentise
Author: Authentise, Inc.
Author-email: engineering@authentise.com
License: AGPLv3
Platform: UNKNOWN
